pydantic_extension/model_slicing/__init__.py
pydantic_extension/model_slicing/mixin.py
pydantic_extension-0.0.5.dist-info/licenses/LICENCE
pydantic_extension-0.0.5.dist-info/METADATA
pydantic_extension-0.0.5.dist-info/WHEEL
pydantic_extension-0.0.5.dist-info/top_level.txt
pydantic_extension-0.0.5.dist-info/RECORD
