Metadata-Version: 2.4
Name: pydantic-extension
Version: 0.0.5
Summary: Handy pydantic extension for advanced slicing and FASTAPI, LLM context awareness
Author-email: HumbleMat <humblemat@gmail.com>
License-Expression: MIT
Project-URL: Homepage, https://github.com/pypa/sampleproject
Project-URL: Issues, https://github.com/pypa/sampleproject/issues
Classifier: Programming Language :: Python :: 3
Classifier: Operating System :: OS Independent
Requires-Python: >=3.9
License-File: LICENCE
Dynamic: license-file
